analytics_eda/__init__.py
analytics_eda/bivariate/__init__.py
analytics_eda/bivariate/bivariate_numeric_categorical/__init__.py
analytics_eda/bivariate/bivariate_numeric_categorical/bivariate_numeric_categorical_analysis.py
analytics_eda/bivariate/bivariate_numeric_categorical/bivariate_numeric_categorical_tests.py
analytics_eda/bivariate/bivariate_numeric_categorical/compute_overlap_metrics.py
analytics_eda/core/__init__.py
analytics_eda/core/clean_series.py
analytics_eda/core/explore_data.py
analytics_eda/core/missing_data_analysis.py
analytics_eda/core/categorical/__init__.py
analytics_eda/core/categorical/categorical_distribution_analysis.py
analytics_eda/core/categorical/categorical_inferential_analysis.py
analytics_eda/core/categorical/validate_categorical_named_series.py
analytics_eda/core/numeric/__init__.py
analytics_eda/core/numeric/assess_normality_and_transform.py
analytics_eda/core/numeric/descriptive_statistics.py
analytics_eda/core/numeric/distribution_fit_assessment.py
analytics_eda/core/numeric/is_discrete.py
analytics_eda/core/numeric/normality_assessment.py
analytics_eda/core/numeric/numeric_distribution_analysis.py
analytics_eda/core/numeric/numeric_distribution_visualizations.py
analytics_eda/core/numeric/numeric_inferential_analysis.py
analytics_eda/core/numeric/numeric_outlier_analysis.py
analytics_eda/core/numeric/report_binning_rules.py
analytics_eda/core/numeric/select_normality_transforms.py
analytics_eda/core/numeric/validate_numeric_named_series.py
analytics_eda/core/reporting/__init__.py
analytics_eda/core/reporting/sanitize_json.py
analytics_eda/core/reporting/write_json_report.py
analytics_eda/univariate/__init__.py
analytics_eda/univariate/categorical/__init__.py
analytics_eda/univariate/categorical/batch_univariate_categorical_analysis.py
analytics_eda/univariate/categorical/univariate_categorical_analysis.py
analytics_eda/univariate/numeric/__init__.py
analytics_eda/univariate/numeric/batch_univariate_numeric_analysis.py
analytics_eda-0.1.18.dist-info/licenses/LICENSE
analytics_eda-0.1.18.dist-info/licenses/NOTICE
analytics_eda-0.1.18.dist-info/METADATA
analytics_eda-0.1.18.dist-info/WHEEL
analytics_eda-0.1.18.dist-info/top_level.txt
analytics_eda-0.1.18.dist-info/RECORD
